[
	{
		"id": 0,
		"title": "Первое мероприятие",
		"start": "2020-05-15",
		"end": "2020-05-20",
		"extendedProps": "",
		"eventConstraint": "",
		"eventOverlap": "",
		"eventAllow": "",
		"eventClassNames": "",
		"eventContent": "<div class='text'><h3>Заголовок первого мероприятия</h3><p>Большой текст-описание первого мероприятия</p></div>"
	},
	{
		"id": 5,
		"title": "Шестое мероприятие",
		"start": "2020-06-30",
		"end": "2020-07-04",
		"extendedProps": "",
		"eventConstraint": "",
		"eventOverlap": "",
		"eventAllow": "",
		"eventClassNames": "",
		"eventContent": "<div class='text'><h3>Заголовок шестого мероприятия</h3><p>Большой текст-описание третьего мероприятия</p></div>"
	}
]
